{
  "generatedAt": "2026-07-18T19:32:24.222Z",
  "rail": {
    "servicesTracked": 1157,
    "modelled": 104,
    "confident": 93,
    "darwinLeadMin": 15,
    "samples": [
      {
        "crs": "FST",
        "std": "22:54",
        "destination": "Grays",
        "platform": "3",
        "confidence": 1,
        "n": 5
      },
      {
        "crs": "BFR",
        "std": "22:37",
        "destination": "Peterborough",
        "platform": "2",
        "confidence": 1,
        "n": 5
      },
      {
        "crs": "BFR",
        "std": "22:42",
        "destination": "Bedford",
        "platform": "2",
        "confidence": 1,
        "n": 8
      },
      {
        "crs": "CLJ",
        "std": "22:18",
        "destination": "Stratford (London)",
        "platform": "1",
        "confidence": 1,
        "n": 8
      },
      {
        "crs": "ECR",
        "std": "22:30",
        "destination": "London Victoria",
        "platform": "4",
        "confidence": 1,
        "n": 5
      },
      {
        "crs": "SRA",
        "std": "22:13",
        "destination": "Richmond",
        "platform": "1",
        "confidence": 1,
        "n": 7
      },
      {
        "crs": "VXH",
        "std": "22:32",
        "destination": "London Waterloo",
        "platform": "7",
        "confidence": 1,
        "n": 6
      },
      {
        "crs": "VXH",
        "std": "22:36",
        "destination": "London Waterloo",
        "platform": "7",
        "confidence": 1,
        "n": 7
      },
      {
        "crs": "ECR",
        "std": "22:45",
        "destination": "London Victoria",
        "platform": "4",
        "confidence": 1,
        "n": 5
      },
      {
        "crs": "PAD",
        "std": "22:30",
        "destination": "Bedwyn",
        "platform": "10",
        "confidence": 1,
        "n": 5
      },
      {
        "crs": "LBG",
        "std": "22:36",
        "destination": "Bedford",
        "platform": "5",
        "confidence": 1,
        "n": 5
      },
      {
        "crs": "STP",
        "std": "22:51",
        "destination": "Bedford",
        "platform": "B",
        "confidence": 1,
        "n": 7
      }
    ]
  },
  "headway": {
    "cells": 20747,
    "usable": 45,
    "ready": false,
    "examples": [
      {
        "line": "jubilee",
        "station": "940GZZLUSWK",
        "band": "wd-07",
        "n": 20,
        "p50": 143,
        "p90": 263
      },
      {
        "line": "elizabeth",
        "station": "910GBONDST",
        "band": "wd-07",
        "n": 20,
        "p50": 188,
        "p90": 188
      },
      {
        "line": "elizabeth",
        "station": "910GBONDST",
        "band": "wd-08",
        "n": 22,
        "p50": 143,
        "p90": 233
      },
      {
        "line": "elizabeth",
        "station": "910GTOTCTRD",
        "band": "wd-07",
        "n": 22,
        "p50": 188,
        "p90": 188
      },
      {
        "line": "elizabeth",
        "station": "910GTOTCTRD",
        "band": "wd-17",
        "n": 23,
        "p50": 143,
        "p90": 203
      },
      {
        "line": "elizabeth",
        "station": "910GTOTCTRD",
        "band": "wd-19",
        "n": 20,
        "p50": 188,
        "p90": 188
      }
    ]
  },
  "coverage": {
    "days": 7,
    "firstEvent": "2026-07-12T10:30:30.915Z",
    "lastEvent": "2026-07-18T19:12:11.236Z",
    "events": 734,
    "incidents": 85,
    "unplanned": 80,
    "planned": 5,
    "runObservations": 176951,
    "modelCells": 84278
  },
  "storage": {
    "eventsBytes": 287456,
    "runtimesBytes": 2959483,
    "platformsBytes": 0,
    "crowdingBytes": 2309670,
    "perDayBytes": 793801
  },
  "readiness": [
    {
      "cause": "train-fault",
      "feature": "Broken-down train — “how long will this last?”",
      "have": 29,
      "need": 20,
      "perDay": 4.14,
      "ready": true,
      "etaDays": [
        0,
        0
      ],
      "medianMin": 80,
      "p90Min": 754
    },
    {
      "cause": "signal-failure",
      "feature": "Signal failure — “how long will this last?”",
      "have": 19,
      "need": 20,
      "perDay": 2.71,
      "ready": false,
      "etaDays": [
        1,
        1
      ],
      "medianMin": 107,
      "p90Min": 1218
    },
    {
      "cause": "other",
      "feature": "Unclassified disruption",
      "have": 14,
      "need": 20,
      "perDay": 2,
      "ready": false,
      "etaDays": [
        1,
        5
      ],
      "medianMin": 27,
      "p90Min": 326
    },
    {
      "cause": "fire-alert",
      "feature": "Fire alert — “is it worth waiting?”",
      "have": 11,
      "need": 20,
      "perDay": 1.57,
      "ready": false,
      "etaDays": [
        3,
        9
      ],
      "medianMin": 80,
      "p90Min": 1431
    },
    {
      "cause": "trespass",
      "feature": "Trespass — “is it worth waiting?”",
      "have": 2,
      "need": 20,
      "perDay": 0.29,
      "ready": false,
      "etaDays": [
        39,
        87
      ],
      "medianMin": 94,
      "p90Min": 136
    },
    {
      "cause": "customer-incident",
      "feature": "Customer taken ill — “is it worth waiting?”",
      "have": 2,
      "need": 20,
      "perDay": 0.29,
      "ready": false,
      "etaDays": [
        39,
        87
      ],
      "medianMin": 90,
      "p90Min": 148
    },
    {
      "cause": "obstruction",
      "feature": "obstruction",
      "have": 1,
      "need": 20,
      "perDay": 0.14,
      "ready": false,
      "etaDays": [
        83,
        183
      ],
      "medianMin": 116,
      "p90Min": 116
    },
    {
      "cause": "power-failure",
      "feature": "Power failure — “how long will this last?”",
      "have": 1,
      "need": 20,
      "perDay": 0.14,
      "ready": false,
      "etaDays": [
        83,
        183
      ],
      "medianMin": 45,
      "p90Min": 45
    }
  ],
  "runReadiness": [
    {
      "line": "northern",
      "n": 27927,
      "ready": true
    },
    {
      "line": "district",
      "n": 22246,
      "ready": true
    },
    {
      "line": "central",
      "n": 20960,
      "ready": true
    },
    {
      "line": "jubilee",
      "n": 16981,
      "ready": true
    },
    {
      "line": "piccadilly",
      "n": 13883,
      "ready": true
    },
    {
      "line": "elizabeth",
      "n": 12644,
      "ready": true
    },
    {
      "line": "victoria",
      "n": 9302,
      "ready": true
    },
    {
      "line": "windrush",
      "n": 9054,
      "ready": true
    },
    {
      "line": "hammersmith-city",
      "n": 8527,
      "ready": true
    },
    {
      "line": "metropolitan",
      "n": 8079,
      "ready": true
    },
    {
      "line": "bakerloo",
      "n": 7979,
      "ready": true
    },
    {
      "line": "mildmay",
      "n": 7093,
      "ready": true
    },
    {
      "line": "circle",
      "n": 4627,
      "ready": true
    },
    {
      "line": "weaver",
      "n": 3116,
      "ready": true
    },
    {
      "line": "lioness",
      "n": 2629,
      "ready": true
    },
    {
      "line": "suffragette",
      "n": 1657,
      "ready": false
    },
    {
      "line": "waterloo-city",
      "n": 182,
      "ready": false
    },
    {
      "line": "liberty",
      "n": 64,
      "ready": false
    }
  ],
  "minIncidents": 20,
  "minRunsReady": 2000,
  "leadTime": {
    "n": 0,
    "medianMinutes": null,
    "samples": []
  },
  "windows": {
    "today": {
      "incidents": 12,
      "unplanned": 10,
      "minorMin": 1213,
      "severeMin": 178,
      "suspendedMin": 156,
      "worstLine": "Metropolitan"
    },
    "week": {
      "incidents": 85,
      "unplanned": 80,
      "minorMin": 13134,
      "severeMin": 5605,
      "suspendedMin": 3452,
      "worstLine": "Weaver (Overground · Liverpool St–Chingford/Enfield/Cheshunt)"
    },
    "all": {
      "incidents": 85,
      "unplanned": 80,
      "minorMin": 13134,
      "severeMin": 5605,
      "suspendedMin": 3452,
      "worstLine": "Weaver (Overground · Liverpool St–Chingford/Enfield/Cheshunt)"
    }
  },
  "worstLines": [
    {
      "line": "Weaver (Overground · Liverpool St–Chingford/Enfield/Cheshunt)",
      "lineId": "weaver",
      "incidents": 5,
      "minorMin": 2309,
      "severeMin": 1933,
      "suspendedMin": 2145,
      "medianMin": 1219
    },
    {
      "line": "Metropolitan",
      "lineId": "metropolitan",
      "incidents": 15,
      "minorMin": 2972,
      "severeMin": 465,
      "suspendedMin": 11,
      "medianMin": 59
    },
    {
      "line": "Mildmay (Overground · Richmond/Clapham Jn–Stratford)",
      "lineId": "mildmay",
      "incidents": 5,
      "minorMin": 593,
      "severeMin": 1266,
      "suspendedMin": 60,
      "medianMin": 148
    },
    {
      "line": "Suffragette (Overground · Gospel Oak–Barking Riverside)",
      "lineId": "suffragette",
      "incidents": 4,
      "minorMin": 778,
      "severeMin": 208,
      "suspendedMin": 592,
      "medianMin": 160
    },
    {
      "line": "Central",
      "lineId": "central",
      "incidents": 8,
      "minorMin": 1430,
      "severeMin": 251,
      "suspendedMin": 17,
      "medianMin": 79
    },
    {
      "line": "Elizabeth line",
      "lineId": "elizabeth",
      "incidents": 5,
      "minorMin": 812,
      "severeMin": 435,
      "suspendedMin": 91,
      "medianMin": 126
    },
    {
      "line": "Victoria",
      "lineId": "victoria",
      "incidents": 8,
      "minorMin": 814,
      "severeMin": 290,
      "suspendedMin": 41,
      "medianMin": 55
    },
    {
      "line": "Piccadilly",
      "lineId": "piccadilly",
      "incidents": 5,
      "minorMin": 1221,
      "severeMin": 79,
      "suspendedMin": 0,
      "medianMin": 65
    },
    {
      "line": "Bakerloo",
      "lineId": "bakerloo",
      "incidents": 5,
      "minorMin": 652,
      "severeMin": 361,
      "suspendedMin": 0,
      "medianMin": 65
    },
    {
      "line": "Windrush (Overground · Highbury–New Cross/Croydon/Crystal Palace)",
      "lineId": "windrush",
      "incidents": 2,
      "minorMin": 18,
      "severeMin": 78,
      "suspendedMin": 689,
      "medianMin": 393
    },
    {
      "line": "Central",
      "lineId": "central",
      "incidents": 6,
      "minorMin": 1686,
      "severeMin": 251,
      "suspendedMin": 17,
      "medianMin": 156
    },
    {
      "line": "Piccadilly",
      "lineId": "piccadilly",
      "incidents": 5,
      "minorMin": 1562,
      "severeMin": 79,
      "suspendedMin": 0,
      "medianMin": 65
    },
    {
      "line": "Bakerloo",
      "lineId": "bakerloo",
      "incidents": 6,
      "minorMin": 796,
      "severeMin": 450,
      "suspendedMin": 2,
      "medianMin": 150
    },
    {
      "line": "Elizabeth line",
      "lineId": "elizabeth",
      "incidents": 3,
      "minorMin": 801,
      "severeMin": 407,
      "suspendedMin": 2,
      "medianMin": 409
    },
    {
      "line": "Victoria",
      "lineId": "victoria",
      "incidents": 7,
      "minorMin": 814,
      "severeMin": 290,
      "suspendedMin": 0,
      "medianMin": 68
    },
    {
      "line": "Northern",
      "lineId": "northern",
      "incidents": 8,
      "minorMin": 666,
      "severeMin": 101,
      "suspendedMin": 31,
      "medianMin": 31
    },
    {
      "line": "DLR",
      "lineId": "dlr",
      "incidents": 3,
      "minorMin": 354,
      "severeMin": 26,
      "suspendedMin": 70,
      "medianMin": 51
    },
    {
      "line": "Jubilee",
      "lineId": "jubilee",
      "incidents": 5,
      "minorMin": 310,
      "severeMin": 67,
      "suspendedMin": 20,
      "medianMin": 50
    },
    {
      "line": "Hammersmith & City",
      "lineId": "hammersmith-city",
      "incidents": 2,
      "minorMin": 193,
      "severeMin": 45,
      "suspendedMin": 0,
      "medianMin": 119
    },
    {
      "line": "Circle",
      "lineId": "circle",
      "incidents": 3,
      "minorMin": 247,
      "severeMin": 0,
      "suspendedMin": 0,
      "medianMin": 80
    },
    {
      "line": "District",
      "lineId": "district",
      "incidents": 2,
      "minorMin": 106,
      "severeMin": 0,
      "suspendedMin": 0,
      "medianMin": 53
    }
  ],
  "recent": [
    {
      "line": "metropolitan",
      "lineName": "Metropolitan",
      "cause": "train-fault",
      "planned": false,
      "start": "2026-07-18T04:46:47.978Z",
      "end": "2026-07-18T18:26:09.785Z",
      "minutes": 819,
      "minorMin": 694,
      "severeMin": 125,
      "suspendedMin": 0,
      "worstSev": 6,
      "peakAfterMin": 30,
      "reason": "Metropolitan Line: Minor delays between Harrow-on-the-Hill and Uxbridge due to train cancellations. GOOD SERVICE on the rest of the line. ",
      "impact": {
        "during": 0,
        "expected": null,
        "pctLost": null,
        "baselineDays": 0
      },
      "trace": [
        {
          "t": "2026-07-18T04:46:47.978Z",
          "sev": 9
        },
        {
          "t": "2026-07-18T05:16:48.926Z",
          "sev": 6
        },
        {
          "t": "2026-07-18T06:32:51.420Z",
          "sev": 9
        },
        {
          "t": "2026-07-18T13:52:00.970Z",
          "sev": 6
        },
        {
          "t": "2026-07-18T14:03:01.497Z",
          "sev": 9
        },
        {
          "t": "2026-07-18T16:35:06.323Z",
          "sev": 6
        },
        {
          "t": "2026-07-18T17:13:08.152Z",
          "sev": 9
        },
        {
          "t": "2026-07-18T18:26:09.785Z",
          "sev": 10
        }
      ],
      "segments": [
        "Aldgate → Uxbridge",
        "Uxbridge → Aldgate",
        "Aldgate → Watford"
      ]
    },
    {
      "line": "district",
      "lineName": "District",
      "cause": "train-fault",
      "planned": false,
      "start": "2026-07-18T17:35:08.846Z",
      "end": "2026-07-18T18:17:09.403Z",
      "minutes": 42,
      "minorMin": 42,
      "severeMin": 0,
      "suspendedMin": 0,
      "worstSev": 9,
      "peakAfterMin": 0,
      "reason": "District Line: Minor delays between Upminster and Barking due to train cancellations. GOOD SERVICE on the rest of the line. ",
      "impact": {
        "during": 0,
        "expected": null,
        "pctLost": null,
        "baselineDays": 0
      },
      "trace": [
        {
          "t": "2026-07-18T17:35:08.846Z",
          "sev": 9
        },
        {
          "t": "2026-07-18T18:17:09.403Z",
          "sev": 10
        }
      ],
      "segments": [
        "Upminster → Ealing Broadway",
        "Ealing Broadway → Upminster",
        "Upminster → Richmond"
      ]
    },
    {
      "line": "northern",
      "lineName": "Northern",
      "cause": "train-fault",
      "planned": false,
      "start": "2026-07-18T16:34:06.470Z",
      "end": "2026-07-18T16:59:07.375Z",
      "minutes": 25,
      "minorMin": 0,
      "severeMin": 25,
      "suspendedMin": 0,
      "worstSev": 6,
      "peakAfterMin": 0,
      "reason": "Northern Line: Severe delays between Euston and Battersea Power Station via Charing Cross due to train cancellations. GOOD SERVICE on the rest of the line. ",
      "impact": {
        "during": 0,
        "expected": null,
        "pctLost": null,
        "baselineDays": 0
      },
      "trace": [
        {
          "t": "2026-07-18T16:34:06.470Z",
          "sev": 6
        },
        {
          "t": "2026-07-18T16:59:07.375Z",
          "sev": 10
        }
      ],
      "segments": [
        "High Barnet → Morden",
        "Morden → High Barnet",
        "Edgware → Morden"
      ]
    },
    {
      "line": "central",
      "lineName": "Central",
      "cause": "train-fault",
      "planned": false,
      "start": "2026-07-18T15:13:03.571Z",
      "end": "2026-07-18T16:31:06.120Z",
      "minutes": 78,
      "minorMin": 78,
      "severeMin": 0,
      "suspendedMin": 0,
      "worstSev": 9,
      "peakAfterMin": 0,
      "reason": "Central Line: Minor delays between North Acton and Ealing Broadway/West Ruislip and between Leytonstone and Epping/Hainault via Newbury Park due to train cancellations. GOOD SERVICE on the rest of the line.  ",
      "impact": {
        "during": 0,
        "expected": null,
        "pctLost": null,
        "baselineDays": 0
      },
      "trace": [
        {
          "t": "2026-07-18T15:13:03.571Z",
          "sev": 9
        },
        {
          "t": "2026-07-18T16:31:06.120Z",
          "sev": 10
        }
      ],
      "segments": [
        "Epping → Ealing Broadway",
        "Ealing Broadway → Epping",
        "Hainault → Ealing Broadway"
      ]
    },
    {
      "line": "hammersmith-city",
      "lineName": "Hammersmith & City",
      "cause": "train-fault",
      "planned": false,
      "start": "2026-07-18T13:52:00.970Z",
      "end": "2026-07-18T16:30:08.678Z",
      "minutes": 158,
      "minorMin": 158,
      "severeMin": 0,
      "suspendedMin": 0,
      "worstSev": 9,
      "peakAfterMin": 0,
      "reason": "Hammersmith and City Line: Minor delays due to train cancellations. ",
      "impact": {
        "during": 0,
        "expected": null,
        "pctLost": null,
        "baselineDays": 0
      },
      "trace": [
        {
          "t": "2026-07-18T13:52:00.970Z",
          "sev": 9
        },
        {
          "t": "2026-07-18T16:30:08.678Z",
          "sev": 10
        }
      ],
      "segments": [
        "Barking → Hammersmith (H&C Line)",
        "Hammersmith (H&C Line) → Barking"
      ]
    },
    {
      "line": "central",
      "lineName": "Central",
      "cause": "train-fault",
      "planned": false,
      "start": "2026-07-18T15:05:03.236Z",
      "end": "2026-07-18T15:12:03.695Z",
      "minutes": 7,
      "minorMin": 7,
      "severeMin": 0,
      "suspendedMin": 0,
      "worstSev": 9,
      "peakAfterMin": 0,
      "reason": "Central Line: Minor delays between North Acton and Ealing Broadway/West Ruislip and between Leytonstone and Epping/Hainault via Newbury Park due to train cancellations. GOOD SERVICE on the rest of the line.  ",
      "impact": {
        "during": 0,
        "expected": null,
        "pctLost": null,
        "baselineDays": 0
      },
      "trace": [
        {
          "t": "2026-07-18T15:05:03.236Z",
          "sev": 9
        },
        {
          "t": "2026-07-18T15:12:03.695Z",
          "sev": 10
        }
      ],
      "segments": [
        "Epping → West Ruislip",
        "West Ruislip → Epping",
        "Hainault → West Ruislip"
      ]
    },
    {
      "line": "northern",
      "lineName": "Northern",
      "cause": "customer-incident",
      "planned": false,
      "start": "2026-07-18T13:52:00.970Z",
      "end": "2026-07-18T14:23:01.901Z",
      "minutes": 31,
      "minorMin": 31,
      "severeMin": 0,
      "suspendedMin": 0,
      "worstSev": 9,
      "peakAfterMin": 0,
      "reason": "Northern Line: Minor delays between Euston and Battersea Power Station via Charing Cross due to an earlier customer incident at East Finchley. GOOD SERVICE on the rest of the line.  ",
      "impact": {
        "during": 0,
        "expected": null,
        "pctLost": null,
        "baselineDays": 0
      },
      "trace": [
        {
          "t": "2026-07-18T13:52:00.970Z",
          "sev": 9
        },
        {
          "t": "2026-07-18T14:23:01.901Z",
          "sev": 10
        }
      ],
      "segments": [
        "High Barnet → Morden",
        "Morden → High Barnet",
        "Edgware → Morden"
      ]
    },
    {
      "line": "elizabeth",
      "lineName": "Elizabeth line",
      "cause": "other",
      "planned": false,
      "start": "2026-07-18T13:52:00.970Z",
      "end": "2026-07-18T13:54:01.302Z",
      "minutes": 2,
      "minorMin": 2,
      "severeMin": 0,
      "suspendedMin": 0,
      "worstSev": 9,
      "peakAfterMin": 0,
      "reason": "Minor delays between Paddington and Abbey Wood due to an earlier obstruction on the overhead power lines at Woolwich. GOOD SERVICE on the rest of the line. ",
      "impact": {
        "during": 0,
        "expected": null,
        "pctLost": null,
        "baselineDays": 0
      },
      "trace": [
        {
          "t": "2026-07-18T13:52:00.970Z",
          "sev": 9
        },
        {
          "t": "2026-07-18T13:54:01.302Z",
          "sev": 10
        }
      ],
      "segments": [
        "Heathrow Terminal 4 → Shenfield",
        "Heathrow Terminal 5 → Shenfield",
        "Shenfield → Heathrow Terminal 4"
      ]
    },
    {
      "line": "elizabeth",
      "lineName": "Elizabeth line",
      "cause": "engineering",
      "planned": true,
      "start": "2026-07-18T03:36:45.334Z",
      "end": "2026-07-18T05:42:49.885Z",
      "minutes": 126,
      "minorMin": 9,
      "severeMin": 28,
      "suspendedMin": 89,
      "worstSev": 3,
      "peakAfterMin": 3,
      "reason": "Bakerloo Line: No service between Elephant & Castle and Lambeth North while we fix a signal failure at Elephant & Castle. MINOR DELAYS on the rest of the line.  ",
      "impact": {
        "during": 0,
        "expected": null,
        "pctLost": null,
        "baselineDays": 0
      },
      "trace": [
        {
          "t": "2026-07-18T08:42:20.346Z",
          "sev": 9
        },
        {
          "t": "2026-07-18T08:45:18.866Z",
          "sev": 3
        },
        {
          "t": "2026-07-18T08:47:19.044Z",
          "sev": 6
        },
        {
          "t": "2026-07-18T10:16:21.677Z",
          "sev": 9
        },
        {
          "t": "2026-07-18T12:37:26.698Z",
          "sev": 10
        }
      ],
      "segments": [
        "Harrow & Wealdstone → Elephant & Castle",
        "Elephant & Castle → Harrow & Wealdstone"
      ]
    },
    {
      "line": "windrush",
      "lineName": "Windrush (Overground · Highbury–New Cross/Croydon/Crystal Palace)",
      "cause": "engineering",
      "planned": true,
      "start": "2026-07-17T21:22:40.839Z",
      "end": "2026-07-18T08:11:17.347Z",
      "minutes": 649,
      "minorMin": 0,
      "severeMin": 0,
      "suspendedMin": 649,
      "worstSev": 3,
      "peakAfterMin": 0,
      "reason": "Windrush Line: No service between New Cross Gate and Crystal Palace/West Croydon due to emergency engineering work at Norwood Junction. London Buses are accepting valid tickets via any reasonable route. GOOD SERVICE on the rest of the line. ",
      "impact": {
        "during": 0,
        "expected": null,
        "pctLost": null,
        "baselineDays": 0
      },
      "trace": [
        {
          "t": "2026-07-17T21:22:40.839Z",
          "sev": 3
        },
        {
          "t": "2026-07-18T08:11:17.347Z",
          "sev": 10
        }
      ],
      "segments": [
        "West Croydon → Highbury & Islington",
        "Highbury & Islington → West Croydon",
        "Crystal Palace → Highbury & Islington"
      ]
    },
    {
      "line": "suffragette",
      "lineName": "Suffragette (Overground · Gospel Oak–Barking Riverside)",
      "cause": "signal-failure",
      "planned": false,
      "start": "2026-07-17T11:53:33.612Z",
      "end": "2026-07-18T08:11:17.347Z",
      "minutes": 1218,
      "minorMin": 737,
      "severeMin": 12,
      "suspendedMin": 469,
      "worstSev": 2,
      "peakAfterMin": 0,
      "reason": "Suffragette Line: No service while we fix a signal failure at Gospel Oak. London Underground are accepting valid tickets via any reasonable route. ",
      "impact": {
        "during": 0,
        "expected": null,
        "pctLost": null,
        "baselineDays": 0
      },
      "trace": [
        {
          "t": "2026-07-17T11:53:33.612Z",
          "sev": 2
        },
        {
          "t": "2026-07-17T19:42:36.929Z",
          "sev": 6
        },
        {
          "t": "2026-07-17T19:54:37.101Z",
          "sev": 9
        },
        {
          "t": "2026-07-18T08:11:17.347Z",
          "sev": 10
        }
      ],
      "segments": [
        "Barking Riverside → Gospel Oak",
        "Gospel Oak → Barking Riverside"
      ]
    },
    {
      "line": "piccadilly",
      "lineName": "Piccadilly",
      "cause": "signal-failure",
      "planned": false,
      "start": "2026-07-17T11:11:32.320Z",
      "end": "2026-07-18T08:11:17.347Z",
      "minutes": 1260,
      "minorMin": 1181,
      "severeMin": 79,
      "suspendedMin": 0,
      "worstSev": 6,
      "peakAfterMin": 511,
      "reason": "Piccadilly Line: Minor delays while we fix a signal failure at South Ealing.  ",
      "impact": {
        "during": 0,
        "expected": null,
        "pctLost": null,
        "baselineDays": 0
      },
      "trace": [
        {
          "t": "2026-07-17T11:11:32.320Z",
          "sev": 9
        },
        {
          "t": "2026-07-17T19:42:36.929Z",
          "sev": 6
        },
        {
          "t": "2026-07-17T21:01:39.860Z",
          "sev": 9
        },
        {
          "t": "2026-07-18T08:11:17.347Z",
          "sev": 10
        }
      ],
      "segments": [
        "Cockfosters → Uxbridge",
        "Uxbridge → Cockfosters",
        "Cockfosters → Heathrow Terminal 5"
      ]
    },
    {
      "line": "mildmay",
      "lineName": "Mildmay (Overground · Richmond/Clapham Jn–Stratford)",
      "cause": "fire-alert",
      "planned": false,
      "start": "2026-07-17T08:20:26.416Z",
      "end": "2026-07-18T08:11:17.347Z",
      "minutes": 1431,
      "minorMin": 0,
      "severeMin": 1371,
      "suspendedMin": 60,
      "worstSev": 2,
      "peakAfterMin": 709,
      "reason": "Mildmay Line: Severe delays due to an earlier fire alert at Stratford.  ",
      "impact": {
        "during": 0,
        "expected": null,
        "pctLost": null,
        "baselineDays": 0
      },
      "trace": [
        {
          "t": "2026-07-17T08:20:26.416Z",
          "sev": 6
        },
        {
          "t": "2026-07-17T09:47:29.306Z",
          "sev": 3
        },
        {
          "t": "2026-07-17T09:49:29.393Z",
          "sev": 6
        },
        {
          "t": "2026-07-17T19:42:36.929Z",
          "sev": 6
        },
        {
          "t": "2026-07-17T19:43:36.702Z",
          "sev": 6
        },
        {
          "t": "2026-07-17T20:09:38.052Z",
          "sev": 2
        },
        {
          "t": "2026-07-17T21:06:39.744Z",
          "sev": 3
        },
        {
          "t": "2026-07-17T21:07:39.974Z",
          "sev": 6
        },
        {
          "t": "2026-07-18T08:11:17.347Z",
          "sev": 10
        }
      ],
      "segments": [
        "Richmond (London) → Stratford (London)",
        "Clapham Junction → Stratford (London)",
        "Stratford (London) → Richmond (London)"
      ]
    },
    {
      "line": "central",
      "lineName": "Central",
      "cause": "train-fault",
      "planned": false,
      "start": "2026-07-17T19:42:36.929Z",
      "end": "2026-07-18T08:11:17.347Z",
      "minutes": 749,
      "minorMin": 749,
      "severeMin": 0,
      "suspendedMin": 0,
      "worstSev": 9,
      "peakAfterMin": 0,
      "reason": "Central Line: Minor delays due to train cancellations. ",
      "impact": {
        "during": 0,
        "expected": null,
        "pctLost": null,
        "baselineDays": 0
      },
      "trace": [
        {
          "t": "2026-07-17T19:42:36.929Z",
          "sev": 9
        },
        {
          "t": "2026-07-18T08:11:17.347Z",
          "sev": 10
        }
      ],
      "segments": [
        "Epping → West Ruislip",
        "West Ruislip → Epping",
        "Hainault → West Ruislip"
      ]
    },
    {
      "line": "victoria",
      "lineName": "Victoria",
      "cause": "train-fault",
      "planned": false,
      "start": "2026-07-17T20:48:39.149Z",
      "end": "2026-07-17T21:14:40.201Z",
      "minutes": 26,
      "minorMin": 26,
      "severeMin": 0,
      "suspendedMin": 0,
      "worstSev": 9,
      "peakAfterMin": 0,
      "reason": "Victoria Line: Minor delays due to an earlier faulty train at King's Cross St. Pancreas. ",
      "impact": {
        "during": 0,
        "expected": null,
        "pctLost": null,
        "baselineDays": 0
      },
      "trace": [
        {
          "t": "2026-07-17T20:48:39.149Z",
          "sev": 9
        },
        {
          "t": "2026-07-17T21:14:40.201Z",
          "sev": 10
        }
      ],
      "segments": [
        "Cockfosters → Uxbridge",
        "Uxbridge → Cockfosters",
        "Cockfosters → Heathrow Terminal 5"
      ]
    },
    {
      "line": "metropolitan",
      "lineName": "Metropolitan",
      "cause": "train-fault",
      "planned": false,
      "start": "2026-07-17T20:40:38.913Z",
      "end": "2026-07-17T21:07:39.974Z",
      "minutes": 27,
      "minorMin": 27,
      "severeMin": 0,
      "suspendedMin": 0,
      "worstSev": 9,
      "peakAfterMin": 0,
      "reason": "Metropolitan Line: Minor delays between Moor Park and Watford due to train cancellations. GOOD SERVICE on the rest of the line. ",
      "impact": {
        "during": 0,
        "expected": null,
        "pctLost": null,
        "baselineDays": 0
      },
      "trace": [
        {
          "t": "2026-07-17T20:40:38.913Z",
          "sev": 9
        },
        {
          "t": "2026-07-17T21:07:39.974Z",
          "sev": 10
        }
      ],
      "segments": [
        "Aldgate → Watford",
        "Watford → Aldgate"
      ]
    },
    {
      "line": "elizabeth",
      "lineName": "Elizabeth line",
      "cause": "signal-failure",
      "planned": false,
      "start": "2026-07-17T19:42:36.929Z",
      "end": "2026-07-17T19:46:36.770Z",
      "minutes": 4,
      "minorMin": 4,
      "severeMin": 0,
      "suspendedMin": 0,
      "worstSev": 9,
      "peakAfterMin": 0,
      "reason": "Minor delays between Whitechapel and Shenfield due to an earlier signal failure at Stratford. GOOD SERVICE on the rest of the line.  ",
      "impact": {
        "during": 0,
        "expected": null,
        "pctLost": null,
        "baselineDays": 0
      },
      "trace": [
        {
          "t": "2026-07-17T19:42:36.929Z",
          "sev": 9
        },
        {
          "t": "2026-07-17T19:46:36.770Z",
          "sev": 10
        }
      ],
      "segments": [
        "Heathrow Terminal 4 → Shenfield",
        "Heathrow Terminal 5 → Shenfield",
        "Shenfield → Heathrow Terminal 4"
      ]
    },
    {
      "line": "victoria",
      "lineName": "Victoria",
      "cause": "signal-failure",
      "planned": false,
      "start": "2026-07-17T08:25:26.744Z",
      "end": "2026-07-17T19:42:36.929Z",
      "minutes": 677,
      "minorMin": 458,
      "severeMin": 219,
      "suspendedMin": 0,
      "worstSev": 6,
      "peakAfterMin": 0,
      "reason": "Victoria Line: Severe delays while we fix a points failure at Walthamstow Central. Tickets are being accepted on London buses, Weaver Line, Suffragette Line, Great Northern, Thameslink, Greater Anglia, South Western Railway services via any reasonable route ",
      "impact": {
        "during": 0,
        "expected": null,
        "pctLost": null,
        "baselineDays": 0
      },
      "trace": [
        {
          "t": "2026-07-17T08:25:26.744Z",
          "sev": 6
        },
        {
          "t": "2026-07-17T12:04:34.240Z",
          "sev": 9
        },
        {
          "t": "2026-07-17T19:42:36.929Z",
          "sev": 10
        }
      ],
      "segments": [
        "Walthamstow Central → Brixton",
        "Brixton → Walthamstow Central"
      ]
    },
    {
      "line": "metropolitan",
      "lineName": "Metropolitan",
      "cause": "train-fault",
      "planned": false,
      "start": "2026-07-17T12:35:06.162Z",
      "end": "2026-07-17T13:34:32.319Z",
      "minutes": 59,
      "minorMin": 59,
      "severeMin": 0,
      "suspendedMin": 0,
      "worstSev": 9,
      "peakAfterMin": 0,
      "reason": "Metropolitan Line: Minor delays between Harrow-on-the-Hill and Uxbridge due to train cancellations.  ",
      "impact": {
        "during": 0,
        "expected": null,
        "pctLost": null,
        "baselineDays": 0
      },
      "trace": [
        {
          "t": "2026-07-17T12:35:06.162Z",
          "sev": 9
        },
        {
          "t": "2026-07-17T13:34:32.319Z",
          "sev": 10
        }
      ],
      "segments": [
        "Aldgate → Uxbridge",
        "Uxbridge → Aldgate"
      ]
    },
    {
      "line": "suffragette",
      "lineName": "Suffragette (Overground · Gospel Oak–Barking Riverside)",
      "cause": "signal-failure",
      "planned": false,
      "start": "2026-07-17T08:20:26.416Z",
      "end": "2026-07-17T11:52:34.112Z",
      "minutes": 212,
      "minorMin": 0,
      "severeMin": 89,
      "suspendedMin": 123,
      "worstSev": 2,
      "peakAfterMin": 89,
      "reason": "Suffragette Line: No service between Barking and Barking Riverside, and SEVERE DELAYS on the rest of line while we fix a signal failure at Barking. London Underground are accepting valid tickets via any reasonable route. ",
      "impact": {
        "during": 0,
        "expected": null,
        "pctLost": null,
        "baselineDays": 0
      },
      "trace": [
        {
          "t": "2026-07-17T08:20:26.416Z",
          "sev": 6
        },
        {
          "t": "2026-07-17T09:49:29.393Z",
          "sev": 2
        },
        {
          "t": "2026-07-17T11:52:34.112Z",
          "sev": 10
        }
      ],
      "segments": [
        "Barking Riverside → Gospel Oak",
        "Gospel Oak → Barking Riverside"
      ]
    },
    {
      "line": "dlr",
      "lineName": "DLR",
      "cause": "power-failure",
      "planned": false,
      "start": "2026-07-17T10:39:30.976Z",
      "end": "2026-07-17T11:24:33.203Z",
      "minutes": 45,
      "minorMin": 0,
      "severeMin": 9,
      "suspendedMin": 36,
      "worstSev": 3,
      "peakAfterMin": 0,
      "reason": "Docklands Light Railway: No service between West India Quay and Lewisham while we fix an electrical fault. GOOD SERVICE on other DLR routes. ",
      "impact": {
        "during": 0,
        "expected": null,
        "pctLost": null,
        "baselineDays": 0
      },
      "trace": [
        {
          "t": "2026-07-17T10:39:30.976Z",
          "sev": 3
        },
        {
          "t": "2026-07-17T10:44:31.177Z",
          "sev": 3
        },
        {
          "t": "2026-07-17T11:15:33.939Z",
          "sev": 6
        },
        {
          "t": "2026-07-17T11:24:33.203Z",
          "sev": 10
        }
      ],
      "segments": [
        "Lewisham DLR Station → Stratford DLR Station",
        "Lewisham DLR Station → Bank DLR Station",
        "Bank DLR Station → Lewisham DLR Station"
      ]
    }
  ]
}